juts/__init__.py
juts/container.py
juts/interface.py
juts/plotwidgets.py
juts/widgets.py
juts/customjobs/__init__.py
juts/customplots/__init__.py
juts/customplots/matplotlib.py
juts/tests/__init__.py
juts/tests/test_container.py
juts/tests/test_interface.py
juts/tests/test_widgets.py
juts-2023.4.2.dist-info/LICENSE
juts-2023.4.2.dist-info/METADATA
juts-2023.4.2.dist-info/WHEEL
juts-2023.4.2.dist-info/top_level.txt
juts-2023.4.2.dist-info/RECORD
