Metadata-Version: 2.1
Name: juts
Version: 2023.4.2
Summary: Jupyter widgets for scheduling processes and visualizing the resulting (live) data
Home-page: https://github.com/riemarc/juts
Author: Marcus Riesmeier
Author-email: gluehen-sierren-0c@icloud.com
License: BSD 3-Clause License
Classifier: Programming Language :: Python :: 3
Classifier: License :: OSI Approved :: BSD License
Classifier: Operating System :: OS Independent
License-File: LICENSE
Requires-Dist: scipy
Requires-Dist: jupyterlab
Requires-Dist: ipywidgets
Requires-Dist: bqplot
Requires-Dist: ipympl
Requires-Dist: ipyvolume
Requires-Dist: yamlordereddictloader
Requires-Dist: nbconvert
Requires-Dist: nbstripout
